pysimultanui_template/__about__.py
pysimultanui_template/__init__.py
pysimultanui_template/contents.py
pysimultanui_template/main.py
pysimultanui_template/mapper.py
pysimultanui_template/maps.py
pysimultanui_template/method_mapper.py
pysimultanui_template/view_manager.py
pysimultanui_template/core/__init__.py
pysimultanui_template/core/class1.py
pysimultanui_template-1.0.0.dist-info/METADATA
pysimultanui_template-1.0.0.dist-info/WHEEL
pysimultanui_template-1.0.0.dist-info/licenses/LICENSE.txt
pysimultanui_template-1.0.0.dist-info/RECORD
