Metadata-Version: 2.3
Name: pysimultanui_template
Version: 1.0.0
Project-URL: Documentation, https://github.com/BÃ¼hler Maximilian/pysimultanui-template#readme
Project-URL: Issues, https://github.com/BÃ¼hler Maximilian/pysimultanui-template/issues
Project-URL: Source, https://github.com/BÃ¼hler Maximilian/pysimultanui-template
Author-email: BÃ¼hler Maximilian <maximilian.buehler@tuwien.ac.at>
License-Expression: MIT
License-File: LICENSE.txt
Classifier: Development Status :: 4 - Beta
Classifier: Programming Language :: Python
Classifier: Programming Language :: Python :: 3.8
Classifier: Programming Language :: Python :: 3.9
Classifier: Programming Language :: Python :: 3.10
Classifier: Programming Language :: Python :: 3.11
Classifier: Programming Language :: Python :: 3.12
Classifier: Programming Language :: Python :: Implementation :: CPython
Classifier: Programming Language :: Python :: Implementation :: PyPy
Requires-Python: >=3.8
